{
    "file": "site\/templates\/contact.php",
    "textdomain": "site--templates--contact-php",
    "translations": {
        "621514e1b818cafa92b50bca7e68977e": {
            "text": "Biziml\u0259 \u0259laq\u0259"
        },
        "22a22c0a9bccfc850221faf3f8e1227a": {
            "text": "Mobil n\u00f6mr\u0259"
        },
        "3919ced7f2e33f678f41ec54fcaa25ee": {
            "text": "\u00dcnvan"
        },
        "5fff270f85ae2d0cb123a3934a77206d": {
            "text": "M\u00fcraci\u0259t g\u00f6nd\u0259r"
        },
        "795c774a879a48fcaad8925ecc0fae69": {
            "text": "M\u00fcraci\u0259t anketi"
        },
        "e1453f58330ed213650a3d976fc921c7": {
            "text": "Mesaj\u0131n\u0131z"
        },
        "5042acac86385851ff2e112045321df0": {
            "text": "Daha \u0259trafl\u0131"
        },
        "147ee6415359685a4b8c0061a5030685": {
            "text": "Tam ad"
        },
        "24b689cd753ddb39d95577594ba2a766": {
            "text": "T\u0259\u015f\u0259kk\u00fcr edirik"
        },
        "3c9f330317f95b2768956818e7b04d98": {
            "text": "M\u00fcraci\u0259tiniz u\u011furla g\u00f6nd\u0259rildi"
        },
        "a942c914534db6fc934be966bb7b7dde": {
            "text": "Yenid\u0259n g\u00f6nd\u0259r"
        }
    }
}